{"Version":3,"Parameters":[{"Id":"Param","GroupId":"","Name":"BackTubes1"},{"Id":"Param2","GroupId":"","Name":"BackTubes2"},{"Id":"Param3","GroupId":"","Name":"BackTubes3"},{"Id":"Param5","GroupId":"","Name":"Tube1_1"},{"Id":"Param6","GroupId":"","Name":"Tube1_2"},{"Id":"Param7","GroupId":"","Name":"Tube1_3"},{"Id":"Param8","GroupId":"","Name":"Tube1_4"},{"Id":"Param31","GroupId":"","Name":"Tube2Inner"},{"Id":"Param27","GroupId":"","Name":"Tube2_1"},{"Id":"Param10","GroupId":"","Name":"Tube2_2"},{"Id":"Param50","GroupId":"","Name":"Tube2_3"},{"Id":"Param13","GroupId":"","Name":"Tube3_1"},{"Id":"Param14","GroupId":"","Name":"Tube3_2"},{"Id":"Param15","GroupId":"","Name":"Tube3_3"},{"Id":"Param17","GroupId":"","Name":"Tube4_1"},{"Id":"Param18","GroupId":"","Name":"Tube4_2"},{"Id":"Param19","GroupId":"","Name":"Tube4_3"},{"Id":"Param35","GroupId":"","Name":"Tube5Inner"},{"Id":"Param21","GroupId":"","Name":"Tube5_1"},{"Id":"Param22","GroupId":"","Name":"Tube5_2"},{"Id":"Param23","GroupId":"","Name":"Tube5_3"},{"Id":"Param25","GroupId":"","Name":"Tube6_1"},{"Id":"Param26","GroupId":"","Name":"Tube6_2"},{"Id":"Param29","GroupId":"","Name":"Tube6_3"},{"Id":"Param28","GroupId":"","Name":"Tube6_4"},{"Id":"Param34","GroupId":"","Name":"Tube7Inner"},{"Id":"Param30","GroupId":"","Name":"Tube7_1"},{"Id":"Param32","GroupId":"","Name":"Tube7_2"},{"Id":"Param33","GroupId":"","Name":"Tube7_3"},{"Id":"Param36","GroupId":"","Name":"Fish1_1"},{"Id":"Param37","GroupId":"","Name":"Fish1_2"},{"Id":"Param51","GroupId":"","Name":"Fish1Fin1"},{"Id":"Param38","GroupId":"","Name":"FishTail1_1"},{"Id":"Param39","GroupId":"","Name":"FishTail1_2"},{"Id":"Param40","GroupId":"","Name":"FishTail1Overall1"},{"Id":"Param42","GroupId":"","Name":"FishTail1Overall2"},{"Id":"Param4","GroupId":"","Name":"FishWrap"},{"Id":"Param9","GroupId":"","Name":"FishTurn"},{"Id":"Param11","GroupId":"","Name":"FishDrawOrder"},{"Id":"Param41","GroupId":"","Name":"Fish2_1"},{"Id":"Param43","GroupId":"","Name":"Fish2_2"},{"Id":"Param52","GroupId":"","Name":"FishTail2Fin"},{"Id":"Param44","GroupId":"","Name":"FishTail2_1"},{"Id":"Param45","GroupId":"","Name":"FishTail2_2"},{"Id":"Param46","GroupId":"","Name":"FishTail1Overall2_1"},{"Id":"Param47","GroupId":"","Name":"FishTail1Overall2_2"},{"Id":"Param12","GroupId":"","Name":"FishWrap2"},{"Id":"Param16","GroupId":"","Name":"FishTurn2"},{"Id":"Param20","GroupId":"","Name":"FishDrawOrder2"},{"Id":"Param48","GroupId":"","Name":"Crab1"},{"Id":"Param49","GroupId":"","Name":"Crab2"}],"ParameterGroups":[],"Parts":[]}
